Metadata-Version: 1.1
Name: emrefirstpack
Version: 0.0.1
Summary: A very basic calculator
Home-page: UNKNOWN
Author: Emre Sevim
Author-email: esevim@ereteam.com
License: MIT
Keywords: calculator
Platform: UNKNOWN
Classifier: Development Status :: 5 - Production/Stable
Classifier: Intended Audience :: Education
Classifier: Operating System :: Microsoft :: Windows :: Windows 10
Classifier: License :: OSI Approved :: MIT License
Classifier: Programming Language :: Python :: 3
